{"nodes": [{"id": "app_services_image_smart_detector_py", "label": "smart_detector.py", "file_type": "code", "source_file": "app\\services\\image\\smart_detector.py", "source_location": "L1"}, {"id": "smart_detector_find_best_cut", "label": "find_best_cut()", "file_type": "code", "source_file": "app\\services\\image\\smart_detector.py", "source_location": "L10"}, {"id": "smart_detector_rationale_1", "label": "Vectorized SmartStitch Pixel Comparison Detector  Optimized for speed using nu", "file_type": "rationale", "source_file": "app\\services\\image\\smart_detector.py", "source_location": "L1"}, {"id": "smart_detector_rationale_14", "label": "Finds the absolute best row to slice the canvas at.", "file_type": "rationale", "source_file": "app\\services\\image\\smart_detector.py", "source_location": "L14"}], "edges": [{"source": "app_services_image_smart_detector_py", "target": "numpy", "relation": "imports", "confidence": "EXTRACTED", "source_file": "app\\services\\image\\smart_detector.py", "source_location": "L7", "weight": 1.0}, {"source": "app_services_image_smart_detector_py", "target": "pil", "relation": "imports_from", "confidence": "EXTRACTED", "source_file": "app\\services\\image\\smart_detector.py", "source_location": "L8", "weight": 1.0}, {"source": "app_services_image_smart_detector_py", "target": "smart_detector_find_best_cut", "relation": "contains", "confidence": "EXTRACTED", "source_file": "app\\services\\image\\smart_detector.py", "source_location": "L10", "weight": 1.0}, {"source": "smart_detector_rationale_1", "target": "app_services_image_smart_detector_py", "relation": "rationale_for", "confidence": "EXTRACTED", "source_file": "app\\services\\image\\smart_detector.py", "source_location": "L1", "weight": 1.0}, {"source": "smart_detector_rationale_14", "target": "smart_detector_find_best_cut", "relation": "rationale_for", "confidence": "EXTRACTED", "source_file": "app\\services\\image\\smart_detector.py", "source_location": "L14", "weight": 1.0}]}